{"_type":"export","__export_format":4,"__export_date":"2024-06-14T13:30:20.933Z","__export_source":"insomnia.desktop.app:v9.2.0","resources":[{"_id":"req_12f7cc596c8046d3aff1c33a0caeefe9","parentId":"wrk_d4ef5327b705442d97b63e2ce221dd53","modified":1718371454426,"created":1718370122251,"url":"http://localhost:8000/api/blog/{{ _._id }}","name":"Get Blog Post by Id","description":"","method":"GET","body":{},"preRequestScript":"","parameters":[],"headers":[{"name":"User-Agent","value":"insomnia/9.2.0"}],"authentication":{},"metaSortKey":-1718370122251,"isPrivate":false,"pathParameters":[],"settingStoreCookies":true,"settingSendCookies":true,"settingDisableRenderRequestBody":false,"settingEncodeUrl":true,"settingRebuildPath":true,"settingFollowRedirects":"global","_type":"request"},{"_id":"wrk_d4ef5327b705442d97b63e2ce221dd53","parentId":null,"modified":1718369404221,"created":1718369404221,"name":"API-Prova2","description":"","scope":"collection","_type":"workspace"},{"_id":"req_02a2f34d38d1437d9945a295670774b6","parentId":"wrk_d4ef5327b705442d97b63e2ce221dd53","modified":1718371260227,"created":1718370093074,"url":"http://localhost:8000/api/blog/{{ _._id }}","name":"Delete Blog Post by Id","description":"","method":"DELETE","body":{},"preRequestScript":"","parameters":[],"headers":[{"name":"User-Agent","value":"insomnia/9.2.0"}],"authentication":{},"metaSortKey":-1718370093074,"isPrivate":false,"pathParameters":[],"settingStoreCookies":true,"settingSendCookies":true,"settingDisableRenderRequestBody":false,"settingEncodeUrl":true,"settingRebuildPath":true,"settingFollowRedirects":"global","_type":"request"},{"_id":"req_11e6409493264550b7069d2ebaac7438","parentId":"wrk_d4ef5327b705442d97b63e2ce221dd53","modified":1718371596933,"created":1718369919565,"url":"http://localhost:8000/api/blog/{{ _._id }}","name":"Update Blog Post by Id","description":"","method":"PUT","body":{"mimeType":"application/json","text":"{\n\t\"title\": \"Dragon Ball\",\n\t\"content\": \"Ki\"\n}"},"preRequestScript":"","parameters":[],"headers":[{"name":"Content-Type","value":"application/json"},{"name":"User-Agent","value":"insomnia/9.2.0"}],"authentication":{},"metaSortKey":-1718369919565,"isPrivate":false,"pathParameters":[],"settingStoreCookies":true,"settingSendCookies":true,"settingDisableRenderRequestBody":false,"settingEncodeUrl":true,"settingRebuildPath":true,"settingFollowRedirects":"global","_type":"request"},{"_id":"req_cf560d6fd69b45b0a6647c63accf3c66","parentId":"wrk_d4ef5327b705442d97b63e2ce221dd53","modified":1718370826064,"created":1718369503004,"url":"http://localhost:8000/api/blog/","name":"Create Blog Post","description":"","method":"POST","body":{"mimeType":"application/json","text":"{\n\t\"title\": \"HunterxHunter\",\n\t\"content\": \"Nen\"\n}"},"preRequestScript":"","parameters":[],"headers":[{"name":"Content-Type","value":"application/json"},{"name":"User-Agent","value":"insomnia/9.2.0"}],"authentication":{},"metaSortKey":-1718369503004,"isPrivate":false,"pathParameters":[],"settingStoreCookies":true,"settingSendCookies":true,"settingDisableRenderRequestBody":false,"settingEncodeUrl":true,"settingRebuildPath":true,"settingFollowRedirects":"global","_type":"request"},{"_id":"req_d8d8ea0a49244c6a9cdef33deb3fb176","parentId":"wrk_d4ef5327b705442d97b63e2ce221dd53","modified":1718369500253,"created":1718369440880,"url":"http://localhost:8000/api/blog/","name":"Get Blog Posts","description":"","method":"GET","body":{},"preRequestScript":"","parameters":[],"headers":[{"name":"User-Agent","value":"insomnia/9.2.0"}],"authentication":{},"metaSortKey":-1718369440880,"isPrivate":false,"pathParameters":[],"settingStoreCookies":true,"settingSendCookies":true,"settingDisableRenderRequestBody":false,"settingEncodeUrl":true,"settingRebuildPath":true,"settingFollowRedirects":"global","_type":"request"},{"_id":"env_26c213b9ec150d2b42e7e33fc5620e908614c399","parentId":"wrk_d4ef5327b705442d97b63e2ce221dd53","modified":1718369980321,"created":1718369404236,"name":"Base Environment","data":{"_id":1},"dataPropertyOrder":{"&":["_id"]},"color":null,"isPrivate":false,"metaSortKey":1718369404236,"_type":"environment"},{"_id":"jar_26c213b9ec150d2b42e7e33fc5620e908614c399","parentId":"wrk_d4ef5327b705442d97b63e2ce221dd53","modified":1718369404238,"created":1718369404238,"name":"Default Jar","cookies":[],"_type":"cookie_jar"}]}